[
    {
        "title": "Array Insertions",
        "description": "Ref at leetcode",
        "link": "https://gitlab.com/-/ide/project/edutech1610/file/tree/main/-/Array_-_Inserting_at_the_Start_End_and_any_given_index_of_an_Array.java",
        "reflinka": "https://leetcode.com/explore/learn/card/fun-with-arrays/525/inserting-items-into-an-array/3244/",
        "reflinkb": "nothing",
        "reflinkc": "nothing"
    },
    {
        "title": "Array Deletions",
        "description": "Ref at leetcode",
        "link": "https://leetcode.com/explore/learn/card/fun-with-arrays/526/deleting-items-from-an-array/3246/",
        "reflinka": "https://leetcode.com/explore/learn/card/fun-with-arrays/526/deleting-items-from-an-array/3246/",
        "reflinkb": "nothing",
        "reflinkc": "nothing"
    },
    {
        "title": "In-Place Algorithm",
        "description": "Ref at GFG\n In-place means that the algorithm does not use extra space for manipulating the input but may require a small though non-constant extra space for its operation. Usually, this space is O(log n), though sometimes anything in O(n) (Smaller than linear) is allowed.",
        "link": "https://www.geeksforgeeks.org/in-place-algorithm/",
        "reflinka": "https://www.geeksforgeeks.org/in-place-algorithm/",
        "reflinkb": "nothing",
        "reflinkc": "nothing"
    }
]
